odoo/addons/base_facturx/README.rst
odoo/addons/base_facturx/__init__.py
odoo/addons/base_facturx/__manifest__.py
odoo/addons/base_facturx/data/zugferd_codes.xml
odoo/addons/base_facturx/i18n/base_facturx.pot
odoo/addons/base_facturx/i18n/base_zugferd.pot
odoo/addons/base_facturx/i18n/de.po
odoo/addons/base_facturx/i18n/es.po
odoo/addons/base_facturx/models/__init__.py
odoo/addons/base_facturx/models/base_facturx.py
odoo/addons/base_facturx/readme/CONFIGURE.rst
odoo/addons/base_facturx/readme/CONTRIBUTORS.rst
odoo/addons/base_facturx/readme/DESCRIPTION.rst
odoo/addons/base_facturx/readme/USAGE.rst
odoo/addons/base_facturx/static/description/icon.png
odoo/addons/base_facturx/static/description/index.html
odoo12_addon_base_facturx-12.0.1.0.0.99.dev6.dist-info/METADATA
odoo12_addon_base_facturx-12.0.1.0.0.99.dev6.dist-info/WHEEL
odoo12_addon_base_facturx-12.0.1.0.0.99.dev6.dist-info/top_level.txt
odoo12_addon_base_facturx-12.0.1.0.0.99.dev6.dist-info/RECORD
